LICENSE
README.md
pyproject.toml
pyconnect/__init__.py
pyconnect/avroparser.py
pyconnect/config.py
pyconnect/core.py
pyconnect/pyconnectsink.py
pyconnect/pyconnectsource.py
pyconnect-0.5.1.dist-info/LICENSE
pyconnect-0.5.1.dist-info/WHEEL
pyconnect-0.5.1.dist-info/METADATA
pyconnect-0.5.1.dist-info/RECORD
